{"info": {"filename": "0080_01_F.jpg", "id": "0080", "gender": "F", "age": 26, "date": "2023-08-01", "skin_type": 3, "sensitive": 0}, "images": {"device": 0, "width": 2136, "height": 3216, "angle": 0, "facepart": 3, "bbox": [268, 1462, 444, 1770]}, "annotations": {"l_perocular_wrinkle": 0}, "equipment": {"l_perocular_wrinkle_Ra": 13.477, "l_perocular_wrinkle_Rmax": 102.2, "l_perocular_wrinkle_Rt": 107.16, "l_perocular_wrinkle_Rz=Rtm": 75.222, "l_perocular_wrinkle_Rp": 53.377, "l_perocular_wrinkle_Rv": 53.782, "l_perocular_wrinkle_Rq": 16.77, "l_perocular_wrinkle_R3z": 43.206}}